README.md
setup.py
vlog/__init__.py
vlog/vlog.py
vlog.egg-info/PKG-INFO
vlog.egg-info/SOURCES.txt
vlog.egg-info/dependency_links.txt
vlog.egg-info/entry_points.txt
vlog.egg-info/requires.txt
vlog.egg-info/top_level.txt