Metadata-Version: 1.0
Name: vlog
Version: 2.0.1
Summary: log functions with arbitrary verbosity
Home-page: https://github.com/jbaber/vlog
Author: John Baber-Lucero
Author-email: pypi@frundle.com
License: GPLv3
Platform: UNKNOWN
